{
  "20241123180000": {
    "prefNumber": 44,
    "observationNumber": 132,
    "pressure": [1016.3, 0],
    "temp": [12, 0],
    "humidity": [45, 0],
    "sun10m": [10, 0],
    "sun1h": [1.0, 0],
    "precipitation10m": [0.0, 0],
    "precipitation1h": [0.0, 0],
    "precipitation3h": [0.0, 0],
    "precipitation24h": [0.0, 0],
    "windDirection": [10, 0],
    "wind": [3.5, 0],
    "maxTempTime": { "hour": 13, "minute": 20 },
    "maxTemp": [15.2, 0],
    "minTempTime": { "hour": 6, "minute": 10 },
    "minTemp": [8.1, 0],
    "gustTime": { "hour": 14, "minute": 30 },
    "gustDirection": [5, 0],
    "gust": [8.2, 0]
  }
}